modules/mux21.v
module mux21(a,b,s,q);
input a,b,s;
output q;
assign q = (~s&a)|(s&b);
endmodule

testbench_combinational/tb_mux21.v
`timescale 1ns/1ps
module mux21_tb();
reg a,b,s;
wire q;
integer i;
mux21 m1(a,b,s,q);
initial
 begin
  $dumpfile("mux.vcd");
  $dumpvars(0, mux21_tb);
  for(i=0;i<8; i=i+1)
   begin
    {s,a,b} = i; #10;
   end
   $finish;
  end
endmodule

mux.vcd
$date
	Thu Jan 29 10:06:05 2026
$end
$version
	Icarus Verilog
$end
$timescale
	1ps
$end
$scope module mux21_tb $end
$var wire 1 ! q $end
$var reg 1 " a $end
$var reg 1 # b $end
$var reg 1 $ s $end
$var integer 32 % i [31:0] $end
$scope module m1 $end
$var wire 1 " a $end
$var wire 1 # b $end
$var wire 1 ! q $end
$var wire 1 $ s $end
$upscope $end
$upscope $end
$enddefinitions $end
$comment Show the parameter values. $end
$dumpall
$end
#0
$dumpvars
b0 %
0$
0#
0"
0!
$end
#10000
1#
b1 %
#20000
1!
1"
0#
b10 %
#30000
1#
b11 %
#40000
0!
1$
0"
0#
b100 %
#50000
1!
1#
b101 %
#60000
0!
1"
0#
b110 %
#70000
1!
1#
b111 %
#80000
b1000 %
